compute_service/__init__.py
compute_service/default.py
compute_service/main.py
compute_service/api/config.py
compute_service/api/crud.py
compute_service/api/database.py
compute_service/api/models.py
compute_service/api/schemas.py
compute_service/queue/base.py
compute_service/queue/capture_std.py
compute_service/queue/crud.py
compute_service/queue/kafka.py
compute_service/queue/local.py
compute_service/queue/socketqueue.py
compute_service/routers/tasks.py
compute_service/service/model.py
compute_service/tests/test_socketqueue.py
compute_service/tests/test_tasks.py
compute_service/tests/test_tasks_validator.py
compute_service/tests/testdb.py
compute_service-0.0.1.dist-info/METADATA
compute_service-0.0.1.dist-info/WHEEL
compute_service-0.0.1.dist-info/top_level.txt
compute_service-0.0.1.dist-info/RECORD
