Metadata-Version: 2.1
Name: compute-service
Version: 0.0.1
Summary: Library to create compute service with REST API and task queue
Author-email: Sergey Bobkov <s.bobkov@grid.kiae.ru>
Classifier: Programming Language :: Python :: 3
Requires-Python: >=3.7
